odoo8_addon_account_bank_statement_period_from_line_date-8.0.1.0.0.99.dev13-py2.7-nspkg.pth
odoo8_addon_account_bank_statement_period_from_line_date-8.0.1.0.0.99.dev13.dist-info/DESCRIPTION.rst
odoo8_addon_account_bank_statement_period_from_line_date-8.0.1.0.0.99.dev13.dist-info/METADATA
odoo8_addon_account_bank_statement_period_from_line_date-8.0.1.0.0.99.dev13.dist-info/RECORD
odoo8_addon_account_bank_statement_period_from_line_date-8.0.1.0.0.99.dev13.dist-info/WHEEL
odoo8_addon_account_bank_statement_period_from_line_date-8.0.1.0.0.99.dev13.dist-info/metadata.json
odoo8_addon_account_bank_statement_period_from_line_date-8.0.1.0.0.99.dev13.dist-info/namespace_packages.txt
odoo8_addon_account_bank_statement_period_from_line_date-8.0.1.0.0.99.dev13.dist-info/top_level.txt
odoo_addons/account_bank_statement_period_from_line_date/README.rst
odoo_addons/account_bank_statement_period_from_line_date/__init__.py
odoo_addons/account_bank_statement_period_from_line_date/__openerp__.py
odoo_addons/account_bank_statement_period_from_line_date/i18n/account_bank_statement_period_from_line_date.pot
odoo_addons/account_bank_statement_period_from_line_date/i18n/de.po
odoo_addons/account_bank_statement_period_from_line_date/i18n/es.po
odoo_addons/account_bank_statement_period_from_line_date/i18n/fr.po
odoo_addons/account_bank_statement_period_from_line_date/i18n/id.po
odoo_addons/account_bank_statement_period_from_line_date/i18n/it.po
odoo_addons/account_bank_statement_period_from_line_date/i18n/nl_NL.po
odoo_addons/account_bank_statement_period_from_line_date/i18n/pt_PT.po
odoo_addons/account_bank_statement_period_from_line_date/i18n/ro_RO.po
odoo_addons/account_bank_statement_period_from_line_date/i18n/sl.po
odoo_addons/account_bank_statement_period_from_line_date/i18n/zh_CN.po
odoo_addons/account_bank_statement_period_from_line_date/model/__init__.py
odoo_addons/account_bank_statement_period_from_line_date/model/account_bank_statement.py
odoo_addons/account_bank_statement_period_from_line_date/model/account_bank_statement_line.py
odoo_addons/account_bank_statement_period_from_line_date/model/account_move_line.py
odoo_addons/account_bank_statement_period_from_line_date/static/description/icon.png
odoo_addons/account_bank_statement_period_from_line_date/tests/__init__.py
odoo_addons/account_bank_statement_period_from_line_date/tests/test_reconciliation.py
