Metadata-Version: 2.0
Name: odoo8-addon-account-bank-statement-period-from-line-date
Version: 8.0.1.0.0.99.dev13
Summary: Use bank transaction (line) date to determine move period
Home-page: https://github.com/OCA/bank-statement-reconcile
Author: Therp BV, Odoo Community Association (OCA)
Author-email: support@odoo-community.org
License: AGPL-3
Platform: UNKNOWN
Classifier: Programming Language :: Python
Classifier: Framework :: Odoo
Classifier: License :: OSI Approved :: GNU Affero General Public License v3
Requires-Python: ~=2.7
Requires-Dist: odoo (<9.0a,>=8.0a)
